monkey_coder/__init__.py
monkey_coder/analyzer.py
monkey_coder/billing.py
monkey_coder/compliance.py
monkey_coder/config.py
monkey_coder/database.py
monkey_coder/feedback_collector.py
monkey_coder/generator.py
monkey_coder/models.py
monkey_coder/monitoring.py
monkey_coder/sandbox_client.py
monkey_coder/security.py
monkey_coder/security_enhanced.py
monkey_coder/sentry_config.py
monkey_coder/agents/__init__.py
monkey_coder/agents/base_agent.py
monkey_coder/agents/communication.py
monkey_coder/agents/communication_network.py
monkey_coder/agents/orchestrator.py
monkey_coder/agents/specialized/__init__.py
monkey_coder/agents/specialized/backend_agent.py
monkey_coder/agents/specialized/code_generator.py
monkey_coder/agents/specialized/devops_agent.py
monkey_coder/agents/specialized/frontend_agent.py
monkey_coder/agents/specialized/security_agent.py
monkey_coder/app/__init__.py
monkey_coder/app/integration_endpoints.py
monkey_coder/app/main.py
monkey_coder/app/streaming_endpoint.py
monkey_coder/app/streaming_endpoints.py
monkey_coder/app/streaming_execute.py
monkey_coder/auth/__init__.py
monkey_coder/auth/api_key_manager.py
monkey_coder/auth/auth_handler.py
monkey_coder/auth/cookie_auth.py
monkey_coder/auth/enhanced_cookie_auth.py
monkey_coder/auth/unified_auth.py
monkey_coder/billing/__init__.py
monkey_coder/billing/cron.py
monkey_coder/billing/models.py
monkey_coder/billing/stripe_client.py
monkey_coder/cache/__init__.py
monkey_coder/cache/base.py
monkey_coder/cache/result_cache.py
monkey_coder/cache/routing_cache.py
monkey_coder/config/__init__.py
monkey_coder/config/cors.py
monkey_coder/config/env_config.py
monkey_coder/config/logging_config.py
monkey_coder/config/mcp_config.py
monkey_coder/config/production_config.py
monkey_coder/config/secrets_config.py
monkey_coder/config/web_search_config.py
monkey_coder/context/__init__.py
monkey_coder/context/context_manager.py
monkey_coder/context/manager.py
monkey_coder/context/simple_manager.py
monkey_coder/core/__init__.py
monkey_coder_core-1.1.1.dist-info/LICENSE
monkey_coder_core-1.1.1.dist-info/METADATA
monkey_coder_core-1.1.1.dist-info/WHEEL
monkey_coder_core-1.1.1.dist-info/entry_points.txt
monkey_coder_core-1.1.1.dist-info/top_level.txt
monkey_coder_core-1.1.1.dist-info/RECORD
